[{"id":"user#Alaina_Wisoky39@yahoo.com","entry":"metadata","type":"user","createdAt":"2020-08-02T18:42:37.900Z","user":{"name":"Hilma Fisher","email":"Alaina_Wisoky39@yahoo.com","password":"1234"}},{"id":"user#Dorothy.Schimmel41@yahoo.com","entry":"metadata","type":"user","createdAt":"2020-08-02T18:42:37.900Z","user":{"name":"Jared Deckow","email":"Dorothy.Schimmel41@yahoo.com","password":"1234"}},{"id":"user#Kaleigh_Grant15@hotmail.com","entry":"metadata","type":"user","createdAt":"2020-08-02T18:42:37.900Z","user":{"name":"Freddie Gottlieb","email":"Kaleigh_Grant15@hotmail.com","password":"1234"}},{"id":"user#Zion_Ankunding54@gmail.com","entry":"metadata","type":"user","createdAt":"2020-08-02T18:42:37.900Z","user":{"name":"Bart Wintheiser","email":"Zion_Ankunding54@gmail.com","password":"1234"}},{"id":"user#Anna.Durgan83@gmail.com","entry":"metadata","type":"user","createdAt":"2020-08-02T18:42:37.900Z","user":{"name":"Justyn Jacobi","email":"Anna.Durgan83@gmail.com","password":"1234"}},{"id":"user#Adah.Rogahn47@yahoo.com","entry":"metadata","type":"user","createdAt":"2020-08-02T18:42:37.900Z","user":{"name":"Ressie Crist","email":"Adah.Rogahn47@yahoo.com","password":"1234"}},{"id":"user#Chelsea.Roob23@yahoo.com","entry":"metadata","type":"user","createdAt":"2020-08-02T18:42:37.900Z","user":{"name":"Queenie Roob","email":"Chelsea.Roob23@yahoo.com","password":"1234"}},{"id":"user#Vella.Schamberger@hotmail.com","entry":"metadata","type":"user","createdAt":"2020-08-02T18:42:37.900Z","user":{"name":"Kory Rempel","email":"Vella.Schamberger@hotmail.com","password":"1234"}},{"id":"user#Matilde.Konopelski31@hotmail.com","entry":"metadata","type":"user","createdAt":"2020-08-02T18:42:37.900Z","user":{"name":"Zack Harber","email":"Matilde.Konopelski31@hotmail.com","password":"1234"}},{"id":"user#Cydney_Bednar@gmail.com","entry":"metadata","type":"user","createdAt":"2020-08-02T18:42:37.900Z","user":{"name":"Natalia Littel IV","email":"Cydney_Bednar@gmail.com","password":"1234"}},{"id":"user#Alaina_Wisoky39@yahoo.com","entry":"lost#f01e20c0-d4ef-11ea-9fb1-dd88b4f7b572","type":"lost","createdAt":"2020-08-02T18:42:37.901Z","notice":{"id":"f01e20c0-d4ef-11ea-9fb1-dd88b4f7b572","name":"Freeman","date":"2020-08-02T18:42:37.900Z","sex":"Macho","imageLinks":"http://lorempixel.com/640/480/animals","commentary":"Sint qui corporis minus fugit exercitationem aut porro harum ab.","marker":{"latitude":-18.9368,"longitude":146.3233},"address":{"name":"","street":"8178 Runolfsdottir Fall","city":"Aylaborough","region":"Alaska","country":"Syrian Arab Republic"}}},{"id":"user#Alaina_Wisoky39@yahoo.com","entry":"lost#f01e47d0-d4ef-11ea-9fb1-dd88b4f7b572","type":"lost","createdAt":"2020-08-02T18:42:37.902Z","notice":{"id":"f01e47d0-d4ef-11ea-9fb1-dd88b4f7b572","name":"Karine","date":"2020-08-02T18:42:37.901Z","sex":"Macho","imageLinks":"http://lorempixel.com/640/480/animals","commentary":"Omnis qui quidem delectus laborum voluptas ut aspernatur enim voluptatem.","marker":{"latitude":62.6079,"longitude":-65.5421},"address":{"name":"","street":"15186 David Plain","city":"East Forrestton","region":"Texas","country":"Jamaica"}}},{"id":"user#Alaina_Wisoky39@yahoo.com","entry":"lost#f01e6ee0-d4ef-11ea-9fb1-dd88b4f7b572","type":"lost","createdAt":"2020-08-02T18:42:37.902Z","notice":{"id":"f01e6ee0-d4ef-11ea-9fb1-dd88b4f7b572","name":"Glen","date":"2020-08-02T18:42:37.902Z","sex":"Macho","imageLinks":"http://lorempixel.com/640/480/animals","commentary":"Dicta voluptate pariatur nam saepe tempora illo error rerum aut.","marker":{"latitude":23.0205,"longitude":18.9285},"address":{"name":"","street":"61026 Champlin Valleys","city":"North Barrettborough","region":"Alabama","country":"Equatorial Guinea"}}},{"id":"user#Alaina_Wisoky39@yahoo.com","entry":"lost#f01e6ee1-d4ef-11ea-9fb1-dd88b4f7b572","type":"lost","createdAt":"2020-08-02T18:42:37.902Z","notice":{"id":"f01e6ee1-d4ef-11ea-9fb1-dd88b4f7b572","name":"Merle","date":"2020-08-02T18:42:37.902Z","sex":"Macho","imageLinks":"http://lorempixel.com/640/480/animals","commentary":"Omnis et explicabo aut culpa est cupiditate occaecati repellat iure.","marker":{"latitude":74.7921,"longitude":-126.1187},"address":{"name":"","street":"2564 Catalina Circles","city":"New Dewitt","region":"West Virginia","country":"Bolivia"}}},{"id":"user#Alaina_Wisoky39@yahoo.com","entry":"lost#f01e6ee2-d4ef-11ea-9fb1-dd88b4f7b572","type":"lost","createdAt":"2020-08-02T18:42:37.902Z","notice":{"id":"f01e6ee2-d4ef-11ea-9fb1-dd88b4f7b572","name":"Queenie","date":"2020-08-02T18:42:37.902Z","sex":"Macho","imageLinks":"http://lorempixel.com/640/480/animals","commentary":"Ut quia quia qui magni voluptatem praesentium veniam enim nemo.","marker":{"latitude":-38.295,"longitude":-130.0097},"address":{"name":"","street":"5563 Crist Ports","city":"Clydebury","region":"Hawaii","country":"Puerto Rico"}}},{"id":"user#Alaina_Wisoky39@yahoo.com","entry":"lost#f01e6ee3-d4ef-11ea-9fb1-dd88b4f7b572","type":"lost","createdAt":"2020-08-02T18:42:37.902Z","notice":{"id":"f01e6ee3-d4ef-11ea-9fb1-dd88b4f7b572","name":"Molly","date":"2020-08-02T18:42:37.902Z","sex":"Macho","imageLinks":"http://lorempixel.com/640/480/animals","commentary":"Necessitatibus similique hic ullam aliquid ducimus et est a ut.","marker":{"latitude":-5.9811,"longitude":8.9925},"address":{"name":"","street":"3895 Eichmann Ford","city":"Schinnerside","region":"Alaska","country":"Solomon Islands"}}},{"id":"user#Alaina_Wisoky39@yahoo.com","entry":"lost#f01e6ee4-d4ef-11ea-9fb1-dd88b4f7b572","type":"lost","createdAt":"2020-08-02T18:42:37.902Z","notice":{"id":"f01e6ee4-d4ef-11ea-9fb1-dd88b4f7b572","name":"Ashton","date":"2020-08-02T18:42:37.902Z","sex":"Macho","imageLinks":"http://lorempixel.com/640/480/animals","commentary":"Natus ut ut eius veniam quod reiciendis ut animi quia.","marker":{"latitude":-9.2878,"longitude":10.2259},"address":{"name":"","street":"844 Maya Fork","city":"New Ilene","region":"Georgia","country":"Gibraltar"}}},{"id":"user#Alaina_Wisoky39@yahoo.com","entry":"lost#f01e6ee5-d4ef-11ea-9fb1-dd88b4f7b572","type":"lost","createdAt":"2020-08-02T18:42:37.902Z","notice":{"id":"f01e6ee5-d4ef-11ea-9fb1-dd88b4f7b572","name":"Romaine","date":"2020-08-02T18:42:37.902Z","sex":"Macho","imageLinks":"http://lorempixel.com/640/480/animals","commentary":"Quisquam id quo sint quia et eaque porro consequatur esse.","marker":{"latitude":-0.5438,"longitude":-94.2789},"address":{"name":"","street":"603 Adolf Bypass","city":"Harrisbury","region":"Mississippi","country":"Portugal"}}},{"id":"user#Alaina_Wisoky39@yahoo.com","entry":"lost#f01e6ee6-d4ef-11ea-9fb1-dd88b4f7b572","type":"lost","createdAt":"2020-08-02T18:42:37.902Z","notice":{"id":"f01e6ee6-d4ef-11ea-9fb1-dd88b4f7b572","name":"Jettie","date":"2020-08-02T18:42:37.902Z","sex":"Macho","imageLinks":"http://lorempixel.com/640/480/animals","commentary":"Cum ducimus quas amet quibusdam quasi consequuntur odit facilis accusamus.","marker":{"latitude":36.5098,"longitude":-115.1585},"address":{"name":"","street":"6656 Lois Rapid","city":"Lake Garrickton","region":"Alaska","country":"Guernsey"}}},{"id":"user#Alaina_Wisoky39@yahoo.com","entry":"lost#f01e6ee7-d4ef-11ea-9fb1-dd88b4f7b572","type":"lost","createdAt":"2020-08-02T18:42:37.903Z","notice":{"id":"f01e6ee7-d4ef-11ea-9fb1-dd88b4f7b572","name":"Zaria","date":"2020-08-02T18:42:37.902Z","sex":"Macho","imageLinks":"http://lorempixel.com/640/480/animals","commentary":"Architecto est asperiores deleniti sequi perspiciatis consectetur ea voluptatem quos.","marker":{"latitude":48.6388,"longitude":-9.8819},"address":{"name":"","street":"05448 Streich Glens","city":"Aniyahhaven","region":"Virginia","country":"Somalia"}}},{"id":"user#Dorothy.Schimmel41@yahoo.com","entry":"found#f01e95f0-d4ef-11ea-9fb1-dd88b4f7b572","type":"found","createdAt":"2020-08-02T18:42:37.903Z","notice":{"id":"f01e95f0-d4ef-11ea-9fb1-dd88b4f7b572","name":"Holly","date":"2020-08-02T18:42:37.903Z","sex":"Macho","imageLinks":"http://lorempixel.com/640/480/animals","commentary":"Laudantium eos ut unde tempora consequatur nihil id consequatur consequatur.","marker":{"latitude":-60.5334,"longitude":145.1514},"address":{"name":"","street":"246 Ron Points","city":"New Sashatown","region":"Oregon","country":"Belize"}}},{"id":"user#Dorothy.Schimmel41@yahoo.com","entry":"found#f01e95f1-d4ef-11ea-9fb1-dd88b4f7b572","type":"found","createdAt":"2020-08-02T18:42:37.903Z","notice":{"id":"f01e95f1-d4ef-11ea-9fb1-dd88b4f7b572","name":"Jessica","date":"2020-08-02T18:42:37.903Z","sex":"Macho","imageLinks":"http://lorempixel.com/640/480/animals","commentary":"Natus earum pariatur et labore possimus optio voluptatem unde nulla.","marker":{"latitude":-35.7741,"longitude":178.8128},"address":{"name":"","street":"6711 Lenny Brook","city":"Haagborough","region":"Vermont","country":"Dominica"}}},{"id":"user#Dorothy.Schimmel41@yahoo.com","entry":"found#f01e95f2-d4ef-11ea-9fb1-dd88b4f7b572","type":"found","createdAt":"2020-08-02T18:42:37.903Z","notice":{"id":"f01e95f2-d4ef-11ea-9fb1-dd88b4f7b572","name":"Bradley","date":"2020-08-02T18:42:37.903Z","sex":"Macho","imageLinks":"http://lorempixel.com/640/480/animals","commentary":"Atque cumque dicta dolorem modi molestiae sit at animi et.","marker":{"latitude":29.5418,"longitude":158.8641},"address":{"name":"","street":"52228 Ondricka Prairie","city":"Lake Kamrenfort","region":"Michigan","country":"Wallis and Futuna"}}},{"id":"user#Dorothy.Schimmel41@yahoo.com","entry":"found#f01e95f3-d4ef-11ea-9fb1-dd88b4f7b572","type":"found","createdAt":"2020-08-02T18:42:37.903Z","notice":{"id":"f01e95f3-d4ef-11ea-9fb1-dd88b4f7b572","name":"Mireille","date":"2020-08-02T18:42:37.903Z","sex":"Macho","imageLinks":"http://lorempixel.com/640/480/animals","commentary":"Velit ab explicabo hic ut dolorum quasi et velit laboriosam.","marker":{"latitude":45.5537,"longitude":20.929},"address":{"name":"","street":"7406 Kihn Islands","city":"East Norris","region":"North Carolina","country":"Kiribati"}}},{"id":"user#Dorothy.Schimmel41@yahoo.com","entry":"found#f01e95f4-d4ef-11ea-9fb1-dd88b4f7b572","type":"found","createdAt":"2020-08-02T18:42:37.903Z","notice":{"id":"f01e95f4-d4ef-11ea-9fb1-dd88b4f7b572","name":"Gabriella","date":"2020-08-02T18:42:37.903Z","sex":"Macho","imageLinks":"http://lorempixel.com/640/480/animals","commentary":"Enim velit eos et nesciunt hic vel magnam sed possimus.","marker":{"latitude":-47.1029,"longitude":-176.1334},"address":{"name":"","street":"39989 Leannon Mission","city":"Port Nestorland","region":"Colorado","country":"Barbados"}}},{"id":"user#Dorothy.Schimmel41@yahoo.com","entry":"found#f01e95f5-d4ef-11ea-9fb1-dd88b4f7b572","type":"found","createdAt":"2020-08-02T18:42:37.903Z","notice":{"id":"f01e95f5-d4ef-11ea-9fb1-dd88b4f7b572","name":"Vidal","date":"2020-08-02T18:42:37.903Z","sex":"Macho","imageLinks":"http://lorempixel.com/640/480/animals","commentary":"Voluptate consequatur velit ullam animi ut distinctio deleniti eius nihil.","marker":{"latitude":-27.9265,"longitude":11.8035},"address":{"name":"","street":"750 Kshlerin Cove","city":"Fritschview","region":"North Dakota","country":"Jordan"}}},{"id":"user#Dorothy.Schimmel41@yahoo.com","entry":"found#f01e95f6-d4ef-11ea-9fb1-dd88b4f7b572","type":"found","createdAt":"2020-08-02T18:42:37.904Z","notice":{"id":"f01e95f6-d4ef-11ea-9fb1-dd88b4f7b572","name":"Eriberto","date":"2020-08-02T18:42:37.903Z","sex":"Macho","imageLinks":"http://lorempixel.com/640/480/animals","commentary":"Adipisci possimus voluptatem sit sit inventore culpa voluptate saepe soluta.","marker":{"latitude":-36.226,"longitude":-179.5074},"address":{"name":"","street":"28205 Kilback Greens","city":"Lake Leola","region":"Colorado","country":"Saint Kitts and Nevis"}}},{"id":"user#Dorothy.Schimmel41@yahoo.com","entry":"found#f01ebd00-d4ef-11ea-9fb1-dd88b4f7b572","type":"found","createdAt":"2020-08-02T18:42:37.904Z","notice":{"id":"f01ebd00-d4ef-11ea-9fb1-dd88b4f7b572","name":"Vanessa","date":"2020-08-02T18:42:37.904Z","sex":"Macho","imageLinks":"http://lorempixel.com/640/480/animals","commentary":"Et sequi vel sapiente magni sit quia alias non ut.","marker":{"latitude":20.8886,"longitude":-66.96},"address":{"name":"","street":"76874 Gusikowski Mountains","city":"Port Herminiofurt","region":"Georgia","country":"Taiwan"}}},{"id":"user#Dorothy.Schimmel41@yahoo.com","entry":"found#f01ebd01-d4ef-11ea-9fb1-dd88b4f7b572","type":"found","createdAt":"2020-08-02T18:42:37.904Z","notice":{"id":"f01ebd01-d4ef-11ea-9fb1-dd88b4f7b572","name":"Cole","date":"2020-08-02T18:42:37.904Z","sex":"Macho","imageLinks":"http://lorempixel.com/640/480/animals","commentary":"Corrupti tenetur perspiciatis qui quis quia facere autem perferendis adipisci.","marker":{"latitude":-0.5865,"longitude":164.2331},"address":{"name":"","street":"663 Michael Island","city":"West Susanatown","region":"Kansas","country":"Botswana"}}},{"id":"user#Dorothy.Schimmel41@yahoo.com","entry":"found#f01ebd02-d4ef-11ea-9fb1-dd88b4f7b572","type":"found","createdAt":"2020-08-02T18:42:37.904Z","notice":{"id":"f01ebd02-d4ef-11ea-9fb1-dd88b4f7b572","name":"Dax","date":"2020-08-02T18:42:37.904Z","sex":"Macho","imageLinks":"http://lorempixel.com/640/480/animals","commentary":"Quis libero iure itaque et ipsa debitis nesciunt nemo rerum.","marker":{"latitude":-62.342,"longitude":169.9099},"address":{"name":"","street":"2743 Mossie Green","city":"Runolfsdottirfort","region":"California","country":"Republic of Korea"}}}]